{
    "modules": [
        {
            "ID": "6E61B172-0DCF-0916-7778-C31E5FA222F6",
            "Name": "BellPlayer",
            "ClassName": "ModengTerm.Terminal.BellPlayer, ModengTerm.Terminal",
            "Inputs": {
            }
        }

        //{
        //    "ID": "F3288AE5-9EC8-60DD-F483-3A88DB928DA1",
        //    "Name": "WatcherAgent",
        //    "ClassName": "ModengTerm.Terminal.Watchers.WatcherAgent, ModengTerm.Terminal",
        //    "Inputs": {
        //    }
        //}
    ]
}